README.rst
setup.cfg
setup.py
golden_retriever.egg-info/PKG-INFO
golden_retriever.egg-info/SOURCES.txt
golden_retriever.egg-info/dependency_links.txt
golden_retriever.egg-info/entry_points.txt
golden_retriever.egg-info/not-zip-safe
golden_retriever.egg-info/requires.txt
golden_retriever.egg-info/top_level.txt
gr/__init__.py
gr/__main__.py
gr/_version.py
gr/gr.py
gr/api/__init__.py
gr/api/events.py
gr/api/utils.py
gr/cli/__init__.py
gr/cli/cli.py
gr/cli/context.py
gr/cli/search.py
gr/cli/tail.py