Metadata-Version: 1.1
Name: golden-retriever
Version: 0.0.2
Summary: Command line utility for Dataloop.IO
Home-page: https://github.com/dataloop/golden-retriever
Author: Steven Acreman
Author-email: steven.acreman@dataloop.io
License: Apache License, Version 2.0
Download-URL: https://github.com/dataloop/golden-retriever/tarball/v0.0.2
Keywords: dataloop monitoring
Platform: any
Classifier: Intended Audience :: Developers
Classifier: Intended Audience :: System Administrators
Classifier: License :: OSI Approved :: Apache Software License
